peloton/__init__.py
peloton/peloton.py
peloton/version.py
peloton-0.0.2.dist-info/LICENSE
peloton-0.0.2.dist-info/METADATA
peloton-0.0.2.dist-info/WHEEL
peloton-0.0.2.dist-info/top_level.txt
peloton-0.0.2.dist-info/RECORD
