Metadata-Version: 2.1
Name: peloton
Version: 0.0.2
Summary: A Python library for Peloton data.
Home-page: https://github.com/geudrik/peloton-client-library
Author: Pat Litke (geudrik)
Author-email: please_use_github_issues@nowhere.com
License: MIT License
Platform: UNKNOWN
Classifier: Programming Language :: Python :: 3
Classifier: License :: OSI Approved :: MIT License
Classifier: Operating System :: OS Independent
Classifier: Development Status :: 5 - Production/Stable
Classifier: Environment :: Console
Classifier: Intended Audience :: Developers
Classifier: Natural Language :: English
Requires-Python: >=3.6
